README.md
setup.cfg
setup.py
congress/__init__.py
congress.egg-info/PKG-INFO
congress.egg-info/SOURCES.txt
congress.egg-info/dependency_links.txt
congress.egg-info/not-zip-safe
congress.egg-info/requires.txt
congress.egg-info/top_level.txt